Workbook

Sheet Cover
B2: The Economics of Transformative AI
B3: Reproducible model of the "Back-of-napkin" AI compute & revenue calculations
B4: Companion workbook to the Part 1+2 report. Prepared for Justin (Arcadia Impact). Build date 2026-06-14.
A6: Purpose
B7: Faithfully reproduces every figure in the source Google Doc, documents and sources all inputs, runs the
B8: logic three independent ways for 2031, and stress-tests the tenuous parameters with a live Monte Carlo.
A10: Sheet guide
B11: Inputs & Sources | C11: Every hardcoded input, its value, units, source link and a confidence flag. Single source of truth.
B12: 2026 Baseline | C12: Concurrent copies, revenue-per-chip, and the Anthropic & DeepSeek per-model case studies.
B13: 2031 Projection | C13: Compute stock, copies, and the three revenue estimates (GPU/chip, model-based, token-based).
B14: Scale & Human | C14: Internet-equivalent output and the LLM-vs-human-cognition comparison.
B15: Monte Carlo | C15: Live 2,000-trial in-sheet simulation of 2031 revenue + human-parity, with percentiles & sensitivity.
B16: Scenario L/B/H | C16: Deterministic low / base / high tornado on each uncertain driver.
A18: Colour legend (financial-model convention)
B19: Blue text | C19: Hardcoded input / assumption you can change
B20: Black text | C20: Formula / calculation
B21: Green text | C21: Link to another sheet in this workbook
B22: Yellow fill | C22: Key assumption that most needs scrutiny
B24: NOTE: Headline figures (e.g. $2T) reproduce the doc exactly. Cells flagged purple carry an analyst note (hover).

Sheet Inputs & Sources
A1: Inputs & Sources
A2: All hardcoded inputs. Blue = change these. Sources are live links; confidence: [E]stablished / [C]ontested / [S]peculative.
B4: Parameter | C4: Value | D4: Unit | E4: Source | F4: Conf. | G4: Analyst note
A5: 2026 BASELINE
B6: Global AI compute stock, 2026 | C6: 20000000 | D6: H100e | E6: Epoch AI (2025 report: ~16.5M end-2025) | F6: C | G6: Doc uses 20M. Epoch published ~16.5M at end-2025; 20M is plausible/slightly conservative for mid-2026 at 3.3x/yr.
B7: H100e to run one frontier copy (1.6T params) | C7: 24 | D7: H100e | E7: DeepSeek V4 (1.6T MoE) deploy footprint | F7: C | G7: ~1.6TB FP8 weights / 80GB = 20 GPUs + KV/overhead ~ 24. Order-of-magnitude.
B8: Industry LLM-serving revenue, 2026 | C8: 100000000000 | D8: USD/yr | E8: Anthropic ~$45B + OpenAI ~$25B + others | F8: C | G8: OpenAI+Anthropic alone ~$70B (doc said $80B). $100B incl. Google/MSFT/xAI/DeepSeek is reasonable.
B9: Anthropic ARR, 2026 | C9: 45000000000 | D9: USD/yr | E9: SemiAnalysis / Simon Willison (run-rate ~$45-47B) | F9: E | G9: Matches doc.
B10: Anthropic inference fleet | C10: 1000000 | D10: H100e | E10: Inferred; total fleet ~2M H100e (1.3M Trn2 + 1M TPUv7 + ~220k GPU) | F10: C | G10: Doc treats 1M as inference-only. Total fleet ~2M, so rev/TOTAL-chip ~$22k.
B11: DeepSeek output throughput | C11: 2100 | D11: tok/s/GPU | E11: Doc (FP4/8 batch inference) | F11: C | G11: Aggregate batched throughput; per-user is far lower.
B12: DeepSeek blended price (doc) | C12: 3.5 | D12: $/Mtok | E12: Doc figure | F12: C | G12: PROBLEM: equals pre-discount OUTPUT price ($3.48). Current V4 output ~$0.87, blended ~$2.17.
B13: DeepSeek utilisation (doc) | C13: 0.4 | D13: frac | E13: Doc "realistic" figure | F13: C | G13: Epoch assumes 5-30% inference utilisation; 40% is optimistic.
B14: Seconds per year | C14: 31536000 | D14: s | E14: 365*24*3600 | F14: E
A15: 2031 PROJECTION
B16: Compute growth rate | C16: 3 | D16: x/yr | E16: Epoch 3.3x/yr; Dario (Dwarkesh) ~3x/yr | F16: E | G16: Doc 3x is slightly below Epoch 3.3x. Conservative.
B17: Projection horizon | C17: 5 | D17: yr | E17: 2026 -> 2031 | F17: E
B18: H100e per frontier copy, 2031 | C18: 200 | D18: H100e | E18: Doc (8x the 2026 footprint) | F18: S | G18: Assumes models get ~8x more compute-hungry per copy.
B19: GPU serving frontier models, 2031 | C19: 2000000000 | D19: H100e | E19: Doc assumption (~40% of 4.86B fleet) | F19: S
B20: Rev/chip HIGH (DeepSeek-derived) | C20: 90000 | D20: USD/yr | E20: Doc DeepSeek case (held flat to 2031) | F20: S | G20: Held constant to 2031 despite falling token prices -> overstates.
B21: Rev/chip LOW (macro avg) | C21: 5000 | D21: USD/yr | E21: Doc macro case ($100B/20M) | F21: C
B22: Concurrent copies, model method | C22: 10000000 | D22: copies | E22: Doc assumption | F22: S
B23: Revenue per copy, 2031 | C23: 200000 | D23: USD/yr | E23: Doc "same as today" | F23: S | G23: INCONSISTENT: 2026 case studies were $1.07M & $2.16M/model, not $200k.
B24: Token capacity, 2031 | C24: 1000000000000 | D24: tok/s | E24: Doc attributes to Epoch | F24: S | G24: Epoch states Q4-2025 capacity 0.5-20B tok/s & 3x/yr; 1T/s by 2031 is consistent but not a direct Epoch quote.
B25: Utilisation, token method | C25: 0.1 | D25: frac | E25: Doc | F25: C
B26: Internet size | C26: 500000000000000 | D26: tokens | E26: EducatingSilicon / chat-log estimates | F26: C | G26: Order-of-magnitude.
B27: White-collar workers, 2031 | C27: 1500000000 | D27: workers | E27: Forrester ~1.25B info workers (2018) | F27: C | G27: Doc 1.5B; current estimates ~1-1.25B.
B28: Human cognition rate (doc) | C28: 1000 | D28: tok/min | E28: Doc | F28: S | G28: Epoch uses 380 wpm thinking ~500 tok/min, 240k tok/day.
B29: Human cognition rate (Epoch) | C29: 240000 | D29: tok/day | E29: Epoch digital-workers piece | F29: C | G29: Alternative basis for cross-check.
B30: Global human wages | C30: 50000000000000 | D30: USD/yr | E30: Dario Amodei (Dwarkesh, 2026) | F30: E | G30: For "% of wages" comparison.

Sheet 2026 Baseline
A1: 2026 Baseline
A2: Green = links to Inputs sheet. "Doc" column = the figure stated in the source Google Doc.
C4: Result | E4: Doc says | F4: Note
A5: Compute capacity
B6: Concurrent frontier copies | C6: ='Inputs & Sources'!$C$6/'Inputs & Sources'!$C$7 -> 833333.33 | E6: 830,000 | F6: 20M / 24. Reproduces (rounded).
B7: Macro revenue per H100e | C7: ='Inputs & Sources'!$C$8/'Inputs & Sources'!$C$6 -> 5000 | E7: $5,000 | F7: $100B / 20M chips.
A9: Case study 1: Anthropic (empirical)
B10: Revenue per chip | C10: ='Inputs & Sources'!$C$9/'Inputs & Sources'!$C$10 -> 45000 | E10: $45,000 | F10: $45B / 1M inference chips.
B11: Number of model copies hosted | C11: ='Inputs & Sources'!$C$10/'Inputs & Sources'!$C$7 -> 41666.667 | E11: 42,000 | F11: 1M / 24.
B12: Revenue per model copy / yr | C12: ='Inputs & Sources'!$C$9/C11 -> 1080000 | E12: $1.07M | F12: $45B / 41,667.
A14: Case study 2: DeepSeek V4 (bottom-up)
B15: Output tokens per GPU / yr | C15: ='Inputs & Sources'!$C$11*'Inputs & Sources'!$C$14 -> 66225600000 | E15: 66.2B | F15: 2,100 tok/s * 31.5M s.
B16: Revenue per GPU / yr @ 100% util | C16: =C15/1000000*'Inputs & Sources'!$C$12 -> 231789.6 | E16: $230k | F16: tokens/1e6 * $3.5/Mtok.
B17: Revenue per GPU / yr @ 40% util | C17: =C16*'Inputs & Sources'!$C$13 -> 92715.84 | E17: $90k | F17: * 40% utilisation.
B18: Revenue per model copy / yr | C18: =C17*'Inputs & Sources'!$C$7 -> 2225180.2 | E18: $2.16M | F18: $90k * 24 GPUs.
B20: Reconciliation: all figures reproduce the doc within rounding. See Note column for the two embedded pricing/fleet caveats (flagged on Inputs sheet).

Sheet 2031 Projection
A1: 2031 Projection
A2: Three independent revenue estimates. The doc adopts the model-based ~$2T figure as its headline.
C4: Result | E4: Doc says | F4: Note
A5: Compute scale
B6: Global compute stock, 2031 | C6: ='Inputs & Sources'!$C$6*'Inputs & Sources'!$C$16^'Inputs & Sources'!$C$17 -> 4860000000 | E6: 4.8B | F6: 20M * 3^5.
B7: Concurrent frontier copies, 2031 | C7: =C6/'Inputs & Sources'!$C$18 -> 24300000 | E7: 24.3M | F7: 4.86B / 200.
B8: ...ratio vs 2026 | C8: =C7/'2026 Baseline'!C6 -> 29.16 | E8: 29x
A10: Method 1 - GPU / revenue-per-chip
B11: Revenue @ $90k/chip (high) | C11: ='Inputs & Sources'!$C$19*'Inputs & Sources'!$C$20 -> 180000000000000 | E11: $180T | F11: 2B chips * $90k. = 1.6x world GDP -> not credible; method breaks down.
B12: Revenue @ $5k/chip (low) | C12: ='Inputs & Sources'!$C$19*'Inputs & Sources'!$C$21 -> 10000000000000 | E12: $10T | F12: 2B chips * $5k.
A14: Method 2 - Model-based (doc headline)
B15: Revenue (10M copies * $200k) | C15: ='Inputs & Sources'!$C$22*'Inputs & Sources'!$C$23 -> 2000000000000 | E15: $2T | F15: INCONSISTENCY: $200k/copy contradicts the 2026 $1.07M-$2.16M/model case studies.
B16: ...if per-copy = $1.07M (2026 Anthropic) | C16: ='Inputs & Sources'!$C$22*'2026 Baseline'!C12 -> 10800000000000 | E16: - | F16: Shows headline depends entirely on the low $200k figure.
A18: Method 3 - Token-based
B19: Effective tokens/sec @10% util | C19: ='Inputs & Sources'!$C$24*'Inputs & Sources'!$C$25 -> 100000000000 | E19: 100B
B20: Tokens per minute | C20: =C19*60 -> 6000000000000 | E20: 6T
B21: Price assumed (implied by doc $5M/min) | C21: 0.83 | E21: $0.83/Mtok | F21: INCONSISTENT with $3.5/Mtok used in DeepSeek calc. Cross-checks below.
B22: Revenue per minute | C22: =C20/1000000*C21 -> 4980000 | E22: $5M
B23: Revenue per year | C23: =C22*60*24*365 -> 2617488000000 | E23: $2.6T | F23: Annualised. Matches doc.
B24: cross-check @ $3.5/Mtok | C24: =C20/1000000*3.5*60*24*365 -> 11037600000000 | E24: - | F24: If DeepSeek price used -> $11T.
B25: cross-check @ $0.50/Mtok | C25: =C20/1000000*0.5*60*24*365 -> 1576800000000 | E25: - | F25: If current DeepSeek output price -> $1.6T.
A27: Trajectory check
B28: Implied 2026->2031 revenue CAGR | C28: =(C15/'Inputs & Sources'!$C$8)^(1/'Inputs & Sources'!$C$17)-1 -> 0.8205642 | E28: ~82% | F28: Compute grows 243x but revenue only ~20x -> revenue per unit compute falls ~12x (price deflation). Coherent but implicit.
B29: Cross-source: Dario Amodei (Dwarkesh 2026) expects "multiple trillions/yr by 2028-29" -> the doc's $2T-by-2031 is conservative vs frontier-lab guidance.

Sheet Scale & Human
A1: Scale & Human comparison
A2: Putting 2031 token volumes in human terms.
C4: Result | E4: Doc says | F4: Note
A5: Internet-scale output
B6: Hours to emit one "whole internet" | C6: ='Inputs & Sources'!$C$26/'2031 Projection'!C20/60 -> 1.3888889 | E6: few hours | F6: 500T / (6T/min) / 60.
A8: vs human cognition (doc basis: 1000 tok/min)
B9: Human token-equiv / min | C9: ='Inputs & Sources'!$C$27*'Inputs & Sources'!$C$28 -> 1500000000000 | E9: 1.5T | F9: 1.5B workers * 1000 tok/min.
B10: LLM : human token ratio | C10: ='2031 Projection'!C20/C9 -> 4 | E10: 4x | F10: LLM 6T/min vs human 1.5T/min.
A12: vs human cognition (Epoch basis: 240k tok/day)
B13: Human token-equiv / day | C13: ='Inputs & Sources'!$C$27*'Inputs & Sources'!$C$29 -> 360000000000000 | E13: - | F13: 1.5B * 240k.
B14: LLM tokens / day | C14: ='2031 Projection'!C20*1440 -> 8.64e+15 | E14: - | F14: 6T/min * 1440.
B15: LLM : human ratio (Epoch basis) | C15: =C14/C13 -> 24 | E15: - | F15: ~24x, not 4x: conclusion is sensitive to the human-cognition assumption.
A17: Revenue vs global wages
B18: Model-based revenue as % of wages | C18: ='2031 Projection'!C15/'Inputs & Sources'!$C$30 -> 0.04 | E18: >5% | F18: $2T / $50T wages = 4%. Doc says ">5% of wages".

Sheet Monte Carlo
A1: Monte Carlo - 2031 revenue & human parity
A2: LIVE 2,000-trial simulation (recalculates on open / F9). Authoritative 300k-trial run is in reproduce.py.
A5: Distribution parameters (blue = editable) | M5: SUMMARY (recalculates live)
B6: Parameter | C6: p1 | D6: p2 | E6: Distribution | F6: Description | M6: Estimate | N6: P5 | O6: P25 | P6: P50 | Q6: P75 | R6: P95 | S6: Mean
B7: growth mean / sd | C7: 3 | D7: 0.45 | E7: Normal, clipped [1.8,4.5] | M7: M1 GPU | N7: =PERCENTILE(E22:E2021,0.05) -> 2.3719702e+12 | O7: =PERCENTILE(E22:E2021,0.25) -> 8.107204e+12 | P7: =PERCENTILE(E22:E2021,0.5) -> 1.6676813e+13 | Q7: =PERCENTILE(E22:E2021,0.75) -> 3.6402398e+13 | R7: =PERCENTILE(E22:E2021,0.95) -> 1.0832225e+14 | S7: =AVERAGE(E22:E2021) -> 3.1373792e+13
B8: h100_2026 lo / hi | C8: 16000000 | D8: 24000000 | E8: Uniform | M8: M2 model | N8: =PERCENTILE(F22:F2021,0.05) -> 4.9131079e+11 | O8: =PERCENTILE(F22:F2021,0.25) -> 1.4253664e+12 | P8: =PERCENTILE(F22:F2021,0.5) -> 2.7557811e+12 | Q8: =PERCENTILE(F22:F2021,0.75) -> 5.7828943e+12 | R8: =PERCENTILE(F22:F2021,0.95) -> 1.7989008e+13 | S8: =AVERAGE(F22:F2021) -> 5.3649524e+12
B9: M1 rev/chip mu / sigma | C9: 9.759647 | D9: 0.755291 | E9: Lognormal (90% CI $5k-$60k) | M9: M3 token | N9: =PERCENTILE(G22:G2021,0.05) -> 4.7237295e+11 | O9: =PERCENTILE(G22:G2021,0.25) -> 2.1651955e+12 | P9: =PERCENTILE(G22:G2021,0.5) -> 5.443564e+12 | Q9: =PERCENTILE(G22:G2021,0.75) -> 1.4893705e+13 | R9: =PERCENTILE(G22:G2021,0.95) -> 6.1582223e+13 | S9: =AVERAGE(G22:G2021) -> 1.6517519e+13
B10: M1 serving-share lo/hi | C10: 0.25 | D10: 0.55 | E10: Uniform | M10: POOLED | N10: =PERCENTILE(H22:H2021,0.05) -> 6.2506083e+11 | O10: =PERCENTILE(H22:H2021,0.25) -> 2.4170625e+12 | P10: =PERCENTILE(H22:H2021,0.5) -> 6.3043342e+12 | Q10: =PERCENTILE(H22:H2021,0.75) -> 1.6986009e+13 | R10: =PERCENTILE(H22:H2021,0.95) -> 6.701361e+13 | S10: =AVERAGE(H22:H2021) -> 1.7165616e+13
B11: M1 price-decline lo/hi | C11: 0.25 | D11: 0.9 | E11: Uniform (rev/chip multiplier to 2031)
B12: M2 copies mu / sigma | C12: 16.065415 | D12: 0.699874 | E12: Lognormal (90% CI 3M-30M) | M12: Probabilities (pooled)
B13: M2 rev/copy mu / sigma | C13: 12.643807 | D13: 0.823116 | E13: Lognormal (90% CI $80k-$1.2M) | M13: P(revenue > $2T) | N13: =COUNTIF(H22:H2021,">2000000000000")/2000 -> 0.792
B14: M3 tok/s mu / sigma | C14: 27.631021 | D14: 1.255412 | E14: Lognormal (80% CI 0.2T-5T) | M14: P(revenue > $1T) | N14: =COUNTIF(H22:H2021,">1000000000000")/2000 -> 0.909
B15: M3 util lo / hi | C15: 0.05 | D15: 0.3 | E15: Uniform (Epoch range) | M15: P(revenue > $10T) | N15: =COUNTIF(H22:H2021,">10000000000000")/2000 -> 0.3825
B16: M3 price mu / sigma | C16: 0.168236 | D16: 0.659287 | E16: Lognormal (90% CI $0.4-$3.5/Mtok)
B17: human workers lo/hi | C17: 1000000000 | D17: 1600000000 | E17: Uniform | M17: Human-parity ratio
B18: human tok/min lo/hi | C18: 400 | D18: 1200 | E18: Uniform | M18: P50 ratio | N18: =MEDIAN(K22:K2021) -> 9.2615685
M19: P(LLM > human-equiv) | N19: =COUNTIF(K22:K2021,">1")/2000 -> 0.9455
A20: Trials (2,000) - columns C..G are the three method revenues + pooled draw + human-parity ratio
B21: Trial | C21: growth | D21: H_2031 | E21: M1 GPU ($) | F21: M2 model ($) | G21: M3 token ($) | H21: Pooled ($) | I21: LLM tok/min | J21: Human/min | K21: Parity x | M21: Doc headline = $2T sits near the 25th percentile of the pooled distribution (i.e. conservative).
B22: 1 | C22: =MEDIAN(1.8,NORMINV(RAND(),$C$7,$D$7),4.5) -> 3.98091 | D22: =($C$8+RAND()*($D$8-$C$8))*C22^5 -> 1.8598829e+10 | E22: =D22*($C$10+RAND()*($D$10-$C$10))*EXP(NORMINV(RAND(),$C$9,$D$9))*($C$11+RAND()*($D$11-$C$11)) -> 3.2122686e+13 | F22: =EXP(NORMINV(RAND(),$C$12,$D$12))*EXP(NORMINV(RAND(),$C$13,$D$13)) -> 1.9952772e+12 | G22: =EXP(NORMINV(RAND(),$C$14,$D$14))*($C$15+RAND()*($D$15-$C$15))*EXP(NORMINV(RAND(),$C$16,$D$16))/1000000*31536000 -> 1.5117536e+12 | H22: =CHOOSE(RANDBETWEEN(1,3),E22,F22,G22) -> 1.5117536e+12 | I22: =EXP(NORMINV(RAND(),$C$14,$D$14))*($C$15+RAND()*($D$15-$C$15))*60 -> 1.8577992e+12 | J22: =($C$17+RAND()*($D$17-$C$17))*($C$18+RAND()*($D$18-$C$18)) -> 5.6986988e+11 | K22: =I22/J22 -> 3.2600409
B23: 2 | C23: =MEDIAN(1.8,NORMINV(RAND(),$C$7,$D$7),4.5) -> 2.4439673 | D23: =($C$8+RAND()*($D$8-$C$8))*C23^5 -> 1.8814659e+09 | E23: =D23*($C$10+RAND()*($D$10-$C$10))*EXP(NORMINV(RAND(),$C$9,$D$9))*($C$11+RAND()*($D$11-$C$11)) -> 8.7788447e+11 | F23: =EXP(NORMINV(RAND(),$C$12,$D$12))*EXP(NORMINV(RAND(),$C$13,$D$13)) -> 1.2811628e+12 | G23: =EXP(NORMINV(RAND(),$C$14,$D$14))*($C$15+RAND()*($D$15-$C$15))*EXP(NORMINV(RAND(),$C$16,$D$16))/1000000*31536000 -> 2.3137529e+12 | H23: =CHOOSE(RANDBETWEEN(1,3),E23,F23,G23) -> 8.7788447e+11 | I23: =EXP(NORMINV(RAND(),$C$14,$D$14))*($C$15+RAND()*($D$15-$C$15))*60 -> 1.4325707e+13 | J23: =($C$17+RAND()*($D$17-$C$17))*($C$18+RAND()*($D$18-$C$18)) -> 5.8654958e+11 | K23: =I23/J23 -> 24.423694
B24: 3 | C24: =MEDIAN(1.8,NORMINV(RAND(),$C$7,$D$7),4.5) -> 3.1712411 | D24: =($C$8+RAND()*($D$8-$C$8))*C24^5 -> 7.1450902e+09 | E24: =D24*($C$10+RAND()*($D$10-$C$10))*EXP(NORMINV(RAND(),$C$9,$D$9))*($C$11+RAND()*($D$11-$C$11)) -> 4.7415105e+13 | F24: =EXP(NORMINV(RAND(),$C$12,$D$12))*EXP(NORMINV(RAND(),$C$13,$D$13)) -> 7.7331989e+11 | G24: =EXP(NORMINV(RAND(),$C$14,$D$14))*($C$15+RAND()*($D$15-$C$15))*EXP(NORMINV(RAND(),$C$16,$D$16))/1000000*31536000 -> 6.0035258e+12 | H24: =CHOOSE(RANDBETWEEN(1,3),E24,F24,G24) -> 6.0035258e+12 | I24: =EXP(NORMINV(RAND(),$C$14,$D$14))*($C$15+RAND()*($D$15-$C$15))*60 -> 1.5933718e+13 | J24: =($C$17+RAND()*($D$17-$C$17))*($C$18+RAND()*($D$18-$C$18)) -> 5.0771456e+11 | K24: =I24/J24 -> 31.38322
B25: 4 | C25: =MEDIAN(1.8,NORMINV(RAND(),$C$7,$D$7),4.5) -> 2.9683081 | D25: =($C$8+RAND()*($D$8-$C$8))*C25^5 -> 3.9437082e+09 | E25: =D25*($C$10+RAND()*($D$10-$C$10))*EXP(NORMINV(RAND(),$C$9,$D$9))*($C$11+RAND()*($D$11-$C$11)) -> 9.4475694e+12 | F25: =EXP(NORMINV(RAND(),$C$12,$D$12))*EXP(NORMINV(RAND(),$C$13,$D$13)) -> 1.9001742e+12 | G25: =EXP(NORMINV(RAND(),$C$14,$D$14))*($C$15+RAND()*($D$15-$C$15))*EXP(NORMINV(RAND(),$C$16,$D$16))/1000000*31536000 -> 6.1297597e+12 | H25: =CHOOSE(RANDBETWEEN(1,3),E25,F25,G25) -> 6.1297597e+12 | I25: =EXP(NORMINV(RAND(),$C$14,$D$14))*($C$15+RAND()*($D$15-$C$15))*60 -> 1.8408047e+12 | J25: =($C$17+RAND()*($D$17-$C$17))*($C$18+RAND()*($D$18-$C$18)) -> 1.055147e+12 | K25: =I25/J25 -> 1.7445954
B26: 5 | C26: =MEDIAN(1.8,NORMINV(RAND(),$C$7,$D$7),4.5) -> 2.691498 | D26: =($C$8+RAND()*($D$8-$C$8))*C26^5 -> 3.1643535e+09 | E26: =D26*($C$10+RAND()*($D$10-$C$10))*EXP(NORMINV(RAND(),$C$9,$D$9))*($C$11+RAND()*($D$11-$C$11)) -> 2.3720661e+12 | F26: =EXP(NORMINV(RAND(),$C$12,$D$12))*EXP(NORMINV(RAND(),$C$13,$D$13)) -> 5.795141e+11 | G26: =EXP(NORMINV(RAND(),$C$14,$D$14))*($C$15+RAND()*($D$15-$C$15))*EXP(NORMINV(RAND(),$C$16,$D$16))/1000000*31536000 -> 3.4225024e+12 | H26: =CHOOSE(RANDBETWEEN(1,3),E26,F26,G26) -> 3.4225024e+12 | I26: =EXP(NORMINV(RAND(),$C$14,$D$14))*($C$15+RAND()*($D$15-$C$15))*60 -> 1.1177219e+13 | J26: =($C$17+RAND()*($D$17-$C$17))*($C$18+RAND()*($D$18-$C$18)) -> 7.9209985e+11 | K26: =I26/J26 -> 14.110871
B27: 6 | C27: =MEDIAN(1.8,NORMINV(RAND(),$C$7,$D$7),4.5) -> 2.6652454 | D27: =($C$8+RAND()*($D$8-$C$8))*C27^5 -> 2.1744972e+09 | E27: =D27*($C$10+RAND()*($D$10-$C$10))*EXP(NORMINV(RAND(),$C$9,$D$9))*($C$11+RAND()*($D$11-$C$11)) -> 8.9368484e+12 | F27: =EXP(NORMINV(RAND(),$C$12,$D$12))*EXP(NORMINV(RAND(),$C$13,$D$13)) -> 9.9074642e+12 | G27: =EXP(NORMINV(RAND(),$C$14,$D$14))*($C$15+RAND()*($D$15-$C$15))*EXP(NORMINV(RAND(),$C$16,$D$16))/1000000*31536000 -> 1.1173215e+14 | H27: =CHOOSE(RANDBETWEEN(1,3),E27,F27,G27) -> 1.1173215e+14 | I27: =EXP(NORMINV(RAND(),$C$14,$D$14))*($C$15+RAND()*($D$15-$C$15))*60 -> 1.9366819e+13 | J27: =($C$17+RAND()*($D$17-$C$17))*($C$18+RAND()*($D$18-$C$18)) -> 1.1960877e+12 | K27: =I27/J27 -> 16.191805
B28: 7 | C28: =MEDIAN(1.8,NORMINV(RAND(),$C$7,$D$7),4.5) -> 2.8217398 | D28: =($C$8+RAND()*($D$8-$C$8))*C28^5 -> 3.2729079e+09 | E28: =D28*($C$10+RAND()*($D$10-$C$10))*EXP(NORMINV(RAND(),$C$9,$D$9))*($C$11+RAND()*($D$11-$C$11)) -> 1.5327433e+13 | F28: =EXP(NORMINV(RAND(),$C$12,$D$12))*EXP(NORMINV(RAND(),$C$13,$D$13)) -> 1.4252333e+12 | G28: =EXP(NORMINV(RAND(),$C$14,$D$14))*($C$15+RAND()*($D$15-$C$15))*EXP(NORMINV(RAND(),$C$16,$D$16))/1000000*31536000 -> 2.550336e+13 | H28: =CHOOSE(RANDBETWEEN(1,3),E28,F28,G28) -> 1.5327433e+13 | I28: =EXP(NORMINV(RAND(),$C$14,$D$14))*($C$15+RAND()*($D$15-$C$15))*60 -> 1.4845073e+12 | J28: =($C$17+RAND()*($D$17-$C$17))*($C$18+RAND()*($D$18-$C$18)) -> 1.1840545e+12 | K28: =I28/J28 -> 1.2537491
B29: 8 | C29: =MEDIAN(1.8,NORMINV(RAND(),$C$7,$D$7),4.5) -> 3.2787766 | D29: =($C$8+RAND()*($D$8-$C$8))*C29^5 -> 6.3756829e+09 | E29: =D29*($C$10+RAND()*($D$10-$C$10))*EXP(NORMINV(RAND(),$C$9,$D$9))*($C$11+RAND()*($D$11-$C$11)) -> 1.0786453e+13 | F29: =EXP(NORMINV(RAND(),$C$12,$D$12))*EXP(NORMINV(RAND(),$C$13,$D$13)) -> 1.1005402e+12 | G29: =EXP(NORMINV(RAND(),$C$14,$D$14))*($C$15+RAND()*($D$15-$C$15))*EXP(NORMINV(RAND(),$C$16,$D$16))/1000000*31536000 -> 2.2216332e+12 | H29: =CHOOSE(RANDBETWEEN(1,3),E29,F29,G29) -> 1.0786453e+13 | I29: =EXP(NORMINV(RAND(),$C$14,$D$14))*($C$15+RAND()*($D$15-$C$15))*60 -> 4.4673085e+13 | J29: =($C$17+RAND()*($D$17-$C$17))*($C$18+RAND()*($D$18-$C$18)) -> 1.3511767e+12 | K29: =I29/J29 -> 33.062356
B30: 9 | C30: =MEDIAN(1.8,NORMINV(RAND(),$C$7,$D$7),4.5) -> 2.4866993 | D30: =($C$8+RAND()*($D$8-$C$8))*C30^5 -> 1.6360635e+09 | E30: =D30*($C$10+RAND()*($D$10-$C$10))*EXP(NORMINV(RAND(),$C$9,$D$9))*($C$11+RAND()*($D$11-$C$11)) -> 4.9094212e+12 | F30: =EXP(NORMINV(RAND(),$C$12,$D$12))*EXP(NORMINV(RAND(),$C$13,$D$13)) -> 9.5702632e+12 | G30: =EXP(NORMINV(RAND(),$C$14,$D$14))*($C$15+RAND()*($D$15-$C$15))*EXP(NORMINV(RAND(),$C$16,$D$16))/1000000*31536000 -> 4.7019158e+13 | H30: =CHOOSE(RANDBETWEEN(1,3),E30,F30,G30) -> 4.7019158e+13 | I30: =EXP(NORMINV(RAND(),$C$14,$D$14))*($C$15+RAND()*($D$15-$C$15))*60 -> 7.0104213e+12 | J30: =($C$17+RAND()*($D$17-$C$17))*($C$18+RAND()*($D$18-$C$18)) -> 1.1234016e+12 | K30: =I30/J30 -> 6.2403516
B31: 10 | C31: =MEDIAN(1.8,NORMINV(RAND(),$C$7,$D$7),4.5) -> 2.762232 | D31: =($C$8+RAND()*($D$8-$C$8))*C31^5 -> 2.9844895e+09 | E31: =D31*($C$10+RAND()*($D$10-$C$10))*EXP(NORMINV(RAND(),$C$9,$D$9))*($C$11+RAND()*($D$11-$C$11)) -> 1.9675284e+13 | F31: =EXP(NORMINV(RAND(),$C$12,$D$12))*EXP(NORMINV(RAND(),$C$13,$D$13)) -> 2.0306768e+13 | G31: =EXP(NORMINV(RAND(),$C$14,$D$14))*($C$15+RAND()*($D$15-$C$15))*EXP(NORMINV(RAND(),$C$16,$D$16))/1000000*31536000 -> 6.5054824e+12 | H31: =CHOOSE(RANDBETWEEN(1,3),E31,F31,G31) -> 6.5054824e+12 | I31: =EXP(NORMINV(RAND(),$C$14,$D$14))*($C$15+RAND()*($D$15-$C$15))*60 -> 2.2768311e+13 | J31: =($C$17+RAND()*($D$17-$C$17))*($C$18+RAND()*($D$18-$C$18)) -> 1.5444744e+12 | K31: =I31/J31 -> 14.741786
B32: 11 | C32: =MEDIAN(1.8,NORMINV(RAND(),$C$7,$D$7),4.5) -> 2.579988 | D32: =($C$8+RAND()*($D$8-$C$8))*C32^5 -> 2.472104e+09 | E32: =D32*($C$10+RAND()*($D$10-$C$10))*EXP(NORMINV(RAND(),$C$9,$D$9))*($C$11+RAND()*($D$11-$C$11)) -> 1.4532922e+13 | F32: =EXP(NORMINV(RAND(),$C$12,$D$12))*EXP(NORMINV(RAND(),$C$13,$D$13)) -> 2.2183295e+12 | G32: =EXP(NORMINV(RAND(),$C$14,$D$14))*($C$15+RAND()*($D$15-$C$15))*EXP(NORMINV(RAND(),$C$16,$D$16))/1000000*31536000 -> 1.7774749e+12 | H32: =CHOOSE(RANDBETWEEN(1,3),E32,F32,G32) -> 1.4532922e+13 | I32: =EXP(NORMINV(RAND(),$C$14,$D$14))*($C$15+RAND()*($D$15-$C$15))*60 -> 1.6553202e+13 | J32: =($C$17+RAND()*($D$17-$C$17))*($C$18+RAND()*($D$18-$C$18)) -> 6.671776e+11 | K32: =I32/J32 -> 24.810788
B33: 12 | C33: =MEDIAN(1.8,NORMINV(RAND(),$C$7,$D$7),4.5) -> 3.209604 | D33: =($C$8+RAND()*($D$8-$C$8))*C33^5 -> 7.8470936e+09 | E33: =D33*($C$10+RAND()*($D$10-$C$10))*EXP(NORMINV(RAND(),$C$9,$D$9))*($C$11+RAND()*($D$11-$C$11)) -> 3.4254038e+13 | F33: =EXP(NORMINV(RAND(),$C$12,$D$12))*EXP(NORMINV(RAND(),$C$13,$D$13)) -> 2.4045783e+12 | G33: =EXP(NORMINV(RAND(),$C$14,$D$14))*($C$15+RAND()*($D$15-$C$15))*EXP(NORMINV(RAND(),$C$16,$D$16))/1000000*31536000 -> 3.0417783e+12 | H33: =CHOOSE(RANDBETWEEN(1,3),E33,F33,G33) -> 3.0417783e+12 | I33: =EXP(NORMINV(RAND(),$C$14,$D$14))*($C$15+RAND()*($D$15-$C$15))*60 -> 2.609983e+13 | J33: =($C$17+RAND()*($D$17-$C$17))*($C$18+RAND()*($D$18-$C$18)) -> 1.1021658e+12 | K33: =I33/J33 -> 23.680494
... B2021: 2000 | C2021: =MEDIAN(1.8,NORMINV(RAND(),$C$7,$D$7),4.5) -> 2.3797442 | D2021: =($C$8+RAND()*($D$8-$C$8))*C2021^5 -> 1.4434008e+09 | E2021: =D2021*($C$10+RAND()*($D$10-$C$10))*EXP(NORMINV(RAND(),$C$9,$D$9))*($C$11+RAND()*($D$11-$C$11)) -> 1.3576195e+13 | F2021: =EXP(NORMINV(RAND(),$C$12,$D$12))*EXP(NORMINV(RAND(),$C$13,$D$13)) -> 3.1320157e+12 | G2021: =EXP(NORMINV(RAND(),$C$14,$D$14))*($C$15+RAND()*($D$15-$C$15))*EXP(NORMINV(RAND(),$C$16,$D$16))/1000000*31536000 -> 2.2739005e+12 | H2021: =CHOOSE(RANDBETWEEN(1,3),E2021,F2021,G2021) -> 2.2739005e+12 | I2021: =EXP(NORMINV(RAND(),$C$14,$D$14))*($C$15+RAND()*($D$15-$C$15))*60 -> 1.4231945e+13 | J2021: =($C$17+RAND()*($D$17-$C$17))*($C$18+RAND()*($D$18-$C$18)) -> 7.3875653e+11 | K2021: =I2021/J2021 -> 19.26473

Sheet Scenario L-B-H
A1: Deterministic scenario / tornado
A2: Token-method revenue ($/yr), one driver at a time low/high, others at base. Shows what moves the answer.
A5: Base case (token method)
B6: tok/s capacity | C6: 1000000000000
B7: utilisation | C7: 0.1
B8: price $/Mtok | C8: 0.83
B9: Base revenue/yr | C9: =C6*C7*C8/1000000*31536000 -> 2617488000000
A11: Tornado (hold others at base)
B12: Driver | C12: Low | D12: High | E12: Rev @ Low | F12: Rev @ High | G12: Swing
B13: tok/s capacity | C13: 300000000000 | D13: 2000000000000 | E13: =C13*$C$7*$C$8/1000000*31536000 -> 785246400000 | F13: =D13*$C$7*$C$8/1000000*31536000 -> 5234976000000 | G13: =ABS(F13-E13) -> 4449729600000
B14: utilisation | C14: 0.05 | D14: 0.3 | E14: =$C$6*C14*$C$8/1000000*31536000 -> 1308744000000 | F14: =$C$6*D14*$C$8/1000000*31536000 -> 7852464000000 | G14: =ABS(F14-E14) -> 6543720000000
B15: price $/Mtok | C15: 0.4 | D15: 3.5 | E15: =$C$6*$C$7*C15/1000000*31536000 -> 1261440000000 | F15: =$C$6*$C$7*D15/1000000*31536000 -> 11037600000000 | G15: =ABS(F15-E15) -> 9776160000000
B17: Capacity and price dominate the spread; utilisation matters least. Mirrors the Spearman ranks in reproduce.py.
