Workbook

Sheet Cover
B2: The Economics of Transformative AI
B3: Reproducible model of the "Back-of-napkin" AI compute & revenue calculations
B4: Companion workbook to the Part 1+2 report. Prepared for Justin (Arcadia Impact). Build date 2026-06-14.
A6: Purpose
B7: Faithfully reproduces every figure in the source Google Doc, documents and sources all inputs, runs the
B8: logic three independent ways for 2031, and stress-tests the tenuous parameters with a live Monte Carlo.
A10: Sheet guide
B11: Inputs & Sources | C11: Every hardcoded input, its value, units, source link and a confidence flag. Single source of truth.
B12: 2026 Baseline | C12: Concurrent copies, revenue-per-chip, and the Anthropic & DeepSeek per-model case studies.
B13: 2031 Projection | C13: Compute stock, copies, and the three revenue estimates (GPU/chip, model-based, token-based).
B14: Scale & Human | C14: Internet-equivalent output and the LLM-vs-human-cognition comparison.
B15: Monte Carlo | C15: Live 2,000-trial in-sheet simulation of 2031 revenue + human-parity, with percentiles & sensitivity.
B16: Scenario L/B/H | C16: Deterministic low / base / high tornado on each uncertain driver.
A18: Colour legend (financial-model convention)
B19: Blue text | C19: Hardcoded input / assumption you can change
B20: Black text | C20: Formula / calculation
B21: Green text | C21: Link to another sheet in this workbook
B22: Yellow fill | C22: Key assumption that most needs scrutiny
B24: NOTE: Headline figures (e.g. $2T) reproduce the doc exactly. Cells flagged purple carry an analyst note (hover).

Sheet Inputs & Sources
A1: Inputs & Sources
A2: All hardcoded inputs. Blue = change these. Sources are live links; confidence: [E]stablished / [C]ontested / [S]peculative.
B4: Parameter | C4: Value | D4: Unit | E4: Source | F4: Conf. | G4: Analyst note
A5: 2026 BASELINE
B6: Global AI compute stock, 2026 | C6: 20000000 | D6: H100e | E6: Epoch AI (2025 report: ~16.5M end-2025) | F6: C | G6: Doc uses 20M. Epoch published ~16.5M at end-2025; 20M is plausible/slightly conservative for mid-2026 at 3.3x/yr.
B7: H100e to run one frontier copy (1.6T params) | C7: =Derivations!$C$13 -> 24 | D7: H100e | E7: DeepSeek V4 (1.6T MoE) deploy footprint | F7: C | G7: Derived from model size & GPU memory (Derivations B).
B8: Industry LLM-serving revenue, 2026 | C8: =Derivations!$C$30 -> 100000000000 | D8: USD/yr | E8: Anthropic ~$45B + OpenAI ~$25B + others | F8: C | G8: Derived: sum of per-company ARR (Derivations F).
B9: Anthropic ARR, 2026 | C9: 45000000000 | D9: USD/yr | E9: SemiAnalysis / Simon Willison (run-rate ~$45-47B) | F9: E | G9: Matches doc.
B10: Anthropic inference fleet | C10: =Derivations!$C$33 -> 800000 | D10: H100e | E10: Inferred; total fleet ~2M H100e (1.3M Trn2 + 1M TPUv7 + ~220k GPU) | F10: C | G10: Derived: total fleet x inference share (Derivations G).
B11: DeepSeek output throughput | C11: =Derivations!$C$17 -> 2099.3446 | D11: tok/s/GPU | E11: Doc (FP4/8 batch inference) | F11: C | G11: Derived from FLOP/s, FLOP/token & decode efficiency (Derivations C).
B12: DeepSeek blended price (derived) | C12: =Derivations!$C$25 -> 1.7454545 | D12: $/Mtok | E12: Doc figure | F12: C | G12: Derived from input/output price & I:O ratio (Derivations E). Replaces the old $3.5 hardcode.
B13: DeepSeek duty-cycle utilisation | C13: =Derivations!$C$20 -> 0.2 | D13: frac | E13: Doc "realistic" figure | F13: C | G13: Now ONLY the time-busy factor; inference-share split out to Derivations D.
B14: Seconds per year | C14: 31536000 | D14: s | E14: 365*24*3600 | F14: E
A15: 2031 PROJECTION
B16: Compute growth rate | C16: 3 | D16: x/yr | E16: Epoch 3.3x/yr; Dario (Dwarkesh) ~3x/yr | F16: E | G16: Doc 3x is slightly below Epoch 3.3x. Conservative.
B17: Projection horizon | C17: 5 | D17: yr | E17: 2026 -> 2031 | F17: E
B18: H100e per frontier copy, 2031 | C18: =Derivations!$C$36 -> 192 | D18: H100e | E18: Doc (8x the 2026 footprint) | F18: S | G18: Derived from 2031 model size & GPU memory (Derivations H).
B19: GPU serving frontier models, 2031 | C19: 2000000000 | D19: H100e | E19: Doc assumption (~40% of 4.86B fleet) | F19: S
B20: Rev/chip HIGH (DeepSeek-derived) | C20: 90000 | D20: USD/yr | E20: Doc DeepSeek case (held flat to 2031) | F20: S | G20: Held constant to 2031 despite falling token prices -> overstates.
B21: Rev/chip LOW (macro avg) | C21: 5000 | D21: USD/yr | E21: Doc macro case ($100B/20M) | F21: C
B22: Concurrent copies, model method | C22: 10000000 | D22: copies | E22: Doc assumption | F22: S
B23: Revenue per copy, 2031 | C23: 200000 | D23: USD/yr | E23: Doc "same as today" | F23: S | G23: INCONSISTENT: 2026 case studies were $1.07M & $2.16M/model, not $200k.
B24: Token capacity, 2031 | C24: 1000000000000 | D24: tok/s | E24: Doc attributes to Epoch | F24: S | G24: Epoch states Q4-2025 capacity 0.5-20B tok/s & 3x/yr; 1T/s by 2031 is consistent but not a direct Epoch quote.
B25: Utilisation, token method | C25: 0.1 | D25: frac | E25: Doc | F25: C
B26: Internet size | C26: 500000000000000 | D26: tokens | E26: EducatingSilicon / chat-log estimates | F26: C | G26: Order-of-magnitude.
B27: White-collar workers, 2031 | C27: 1500000000 | D27: workers | E27: Forrester ~1.25B info workers (2018) | F27: C | G27: Doc 1.5B; current estimates ~1-1.25B.
B28: Human cognition rate (doc) | C28: 1000 | D28: tok/min | E28: Doc | F28: S | G28: Epoch uses 380 wpm thinking ~500 tok/min, 240k tok/day.
B29: Human cognition rate (Epoch) | C29: 240000 | D29: tok/day | E29: Epoch digital-workers piece | F29: C | G29: Alternative basis for cross-check.
B30: Global human wages | C30: 50000000000000 | D30: USD/yr | E30: Dario Amodei (Dwarkesh, 2026) | F30: E | G30: For "% of wages" comparison.

Sheet Derivations
A1: Derivations
A2: Composite inputs built up from primitives. Blue = primitive you can change; black = formula; the Inputs sheet now links here (green) instead of hardcoding these.
A4: A. Hardware & precision (primitives)
B5: H100 peak compute (FP8, dense) | C5: 1.979e+15 | D5: FLOP/s | E5: NVIDIA H100 SXM ~1,979 TFLOP/s FP8 dense.
B6: Bytes per parameter (FP8) | C6: 1 | D6: bytes | E6: FP8 = 1 byte/param.
B7: GPU memory per chip | C7: 80000000000 | D7: bytes | E7: H100 80GB.
A8: B. Frontier model - DeepSeek V4 (1.6T MoE)
B9: Total parameters | C9: 1600000000000 | D9: params | E9: DeepSeek V4 1.6T MoE.
B10: Active parameters (MoE) | C10: 37000000000 | D10: params | E10: ~37B active per token.
B11: FLOP per output token | C11: =2*$C$10 -> 74000000000 | D11: FLOP | E11: 2 x active params (forward pass).
B12: Memory overhead factor (KV cache etc.) | C12: 1.2 | D12: x | E12: Weights + KV cache + activations.
B13: GPUs to hold one copy (2026) | C13: =CEILING($C$9*$C$6*$C$12/$C$7,1) -> 24 | D13: H100e | E13: =total_params x bytes x overhead / gpu mem. -> #NAME?
A14: C. Throughput: converting FLOP/s into tokens/s
B15: Theoretical peak tokens/s/GPU | C15: =$C$5/$C$11 -> 26743.243 | D15: tok/s | E15: #VALUE!
B16: Decode efficiency (memory-bound) | C16: 0.0785 | D16: frac | E16: Decode is bandwidth-bound, not FLOP-bound; only ~8% of FLOP peak is realised. Calibrated to ~2,100 tok/s.
B17: Achieved busy throughput / GPU | C17: =$C$15*$C$16 -> 2099.3446 | D17: tok/s | E17: #VALUE!
A18: D. Utilisation - now TWO separate factors
B19: Inference share of fleet | C19: 0.4 | D19: frac | E19: Fraction of a fleet on inference vs training/experiments (Epoch ~44%).
B20: Duty cycle (time actively serving) | C20: 0.2 | D20: frac | E20: Fraction of the year a serving GPU is actually busy (Epoch realistic 5-30%).
A21: E. Token pricing (build the blend)
B22: Input price | C22: 1.6 | D22: $/Mtok | E22: DeepSeek V4-Pro NovitaAI - OpenRouter
B23: Output price | C23: 3.2 | D23: $/Mtok | E23: DeepSeek V4-Pro NovitaAI - OpenRouter
B24: Input : output token ratio | C24: 10 | D24: x | E24: Ratio of input tokens to output tokens
B25: Blended price (derived) | C25: =($C$22*$C$24+$C$23)/($C$24+1) -> 1.7454545 | D25: $/Mtok
A26: F. Industry 2026 revenue (sum, not a guess)
B27: Anthropic ARR | C27: 45000000000 | D27: $/yr | E27: SemiAnalysis/Willison.
B28: OpenAI ARR | C28: 25000000000 | D28: $/yr | E28: Sacra.
B29: Others (Google/MSFT/xAI/DeepSeek/...) | C29: 30000000000 | D29: $/yr | E29: Estimate to reach industry total.
B30: Industry LLM-serving revenue | C30: =$C$27+$C$28+$C$29 -> 100000000000 | D30: $/yr
A31: G. Anthropic fleet -> inference chips
B32: Anthropic total fleet | C32: 2000000 | D32: H100e | E32: 1.3M Trn2 + 1M TPUv7 + ~220k GPU ~ 2M H100e.
B33: Anthropic inference fleet | C33: =$C$32*$C$19 -> 800000 | D33: H100e
A34: H. 2031 frontier model footprint
B35: 2031 model total parameters | C35: 12800000000000 | D35: params | E35: ~8x the 1.6T (doc assumption).
B36: GPUs to hold one copy (2031) | C36: =CEILING($C$35*$C$6*$C$12/$C$7,1) -> 192 | D36: H100e
A37: I. DeepSeek revenue per GPU/model (2 streams)
B38: Output tokens / GPU / yr | C38: =$C$17*31536000*$C$20 -> 1.3240986e+10 | D38: tokens
B39: Input tokens / GPU / yr | C39: =$C$38*$C$24 -> 1.3240986e+11 | D39: tokens
B40: Revenue / GPU / yr | C40: =$C$38/1000000*$C$23+$C$39/1000000*$C$22 -> 254226.94 | D40: $/yr | E40: output@out_price + input@in_price (priced by stream, not a single blend).
B41: Revenue / model copy / yr | C41: =$C$40*$C$13 -> 6101446.5 | D41: $/yr

Sheet 2026 Baseline
A1: 2026 Baseline
A2: Green = links to Inputs sheet. "Doc" column = the figure stated in the source Google Doc.
C4: Result | E4: Doc says | F4: Note
A5: Compute capacity
B6: Concurrent frontier copies | C6: ='Inputs & Sources'!$C$6/'Inputs & Sources'!$C$7 -> 833333.33 | E6: 830,000 | F6: 20M / 24. Reproduces (rounded).
B7: Macro revenue per H100e | C7: ='Inputs & Sources'!$C$8/'Inputs & Sources'!$C$6 -> 5000 | E7: $5,000 | F7: $100B / 20M chips.
A9: Case study 1: Anthropic (empirical)
B10: Revenue per chip | C10: ='Inputs & Sources'!$C$9/'Inputs & Sources'!$C$10 -> 56250 | E10: $45,000 | F10: $45B / 1M inference chips.
B11: Number of model copies hosted | C11: ='Inputs & Sources'!$C$10/'Inputs & Sources'!$C$7 -> 33333.333 | E11: 42,000 | F11: 1M / 24.
B12: Revenue per model copy / yr | C12: ='Inputs & Sources'!$C$9/C11 -> 1350000 | E12: $1.07M | F12: $45B / 41,667.
A14: Case study 2: DeepSeek V4 (bottom-up)
B15: Output tokens / GPU / yr (busy x duty) | C15: =Derivations!$C$38 -> 1.3240986e+10 | E15: — | F15: busy throughput x sec/yr x duty cycle.
B16: Input tokens / GPU / yr (x I:O ratio) | C16: =Derivations!$C$39 -> 1.3240986e+11 | E16: — | F16: output x 3 (input:output).
B17: Revenue / GPU / yr (output + input) | C17: =Derivations!$C$40 -> 254226.94 | E17: $90k @40% | F17: Priced by stream. Corrected inputs land ~$29k, below Anthropic premium $45k.
B18: Revenue per model copy / yr | C18: =Derivations!$C$41 -> 6101446.5 | E18: $2.16M | F18: =rev/gpu x gpus/copy. -> #NAME?
B20: Reconciliation: all figures reproduce the doc within rounding. See Note column for the two embedded pricing/fleet caveats (flagged on Inputs sheet).

Sheet 2031 Projection
A1: 2031 Projection
A2: Three independent revenue estimates. The doc adopts the model-based ~$2T figure as its headline.
C4: Result | E4: Doc says | F4: Note
A5: Compute scale
B6: Global compute stock, 2031 | C6: ='Inputs & Sources'!$C$6*'Inputs & Sources'!$C$16^'Inputs & Sources'!$C$17 -> 4860000000 | E6: 4.8B | F6: 20M * 3^5.
B7: Concurrent frontier copies, 2031 | C7: =C6/'Inputs & Sources'!$C$18 -> 25312500 | E7: 24.3M | F7: 4.86B / 200.
B8: ...ratio vs 2026 | C8: =C7/'2026 Baseline'!C6 -> 30.375 | E8: 29x
A10: Method 1 - GPU / revenue-per-chip
B11: Revenue @ $90k/chip (high) | C11: ='Inputs & Sources'!$C$19*'Inputs & Sources'!$C$20 -> 180000000000000 | E11: $180T | F11: 2B chips * $90k. = 1.6x world GDP -> not credible; method breaks down.
B12: Revenue @ $5k/chip (low) | C12: ='Inputs & Sources'!$C$19*'Inputs & Sources'!$C$21 -> 10000000000000 | E12: $10T | F12: 2B chips * $5k.
A14: Method 2 - Model-based (doc headline)
B15: Revenue (10M copies * $200k) | C15: ='Inputs & Sources'!$C$22*'Inputs & Sources'!$C$23 -> 2000000000000 | E15: $2T | F15: INCONSISTENCY: $200k/copy contradicts the 2026 $1.07M-$2.16M/model case studies.
B16: ...if per-copy = $1.07M (2026 Anthropic) | C16: ='Inputs & Sources'!$C$22*'2026 Baseline'!C12 -> 13500000000000 | E16: - | F16: Shows headline depends entirely on the low $200k figure.
A18: Method 3 - Token-based
B19: Effective tokens/sec @10% util | C19: ='Inputs & Sources'!$C$24*'Inputs & Sources'!$C$25 -> 100000000000 | E19: 100B
B20: Tokens per minute | C20: =C19*60 -> 6000000000000 | E20: 6T
B21: Output price (derived; capacity = generation tokens) | C21: =Derivations!$C$23 -> 3.2 | E21: $0.83 implied | F21: Was a back-solved $0.83. Now the actual output price; revenue becomes a forward calc.
B22: Revenue per minute | C22: =C20/1000000*C21 -> 19200000 | E22: $5M
B23: Revenue per year | C23: =C22*60*24*365 -> 10091520000000 | E23: $2.6T | F23: Annualised. Matches doc.
B24: cross-check @ $3.5/Mtok | C24: =C20/1000000*3.5*60*24*365 -> 11037600000000 | E24: - | F24: If DeepSeek price used -> $11T.
B25: cross-check @ $0.50/Mtok | C25: =C20/1000000*0.5*60*24*365 -> 1576800000000 | E25: - | F25: If current DeepSeek output price -> $1.6T.
A27: Trajectory check
B28: Implied 2026->2031 revenue CAGR | C28: =(C15/'Inputs & Sources'!$C$8)^(1/'Inputs & Sources'!$C$17)-1 -> 0.8205642 | E28: ~82% | F28: Compute grows 243x but revenue only ~20x -> revenue per unit compute falls ~12x (price deflation). Coherent but implicit.
B29: Cross-source: Dario Amodei (Dwarkesh 2026) expects "multiple trillions/yr by 2028-29" -> the doc's $2T-by-2031 is conservative vs frontier-lab guidance.

Sheet Scale & Human
A1: Scale & Human comparison
A2: Putting 2031 token volumes in human terms.
C4: Result | E4: Doc says | F4: Note
A5: Internet-scale output
B6: Hours to emit one "whole internet" | C6: ='Inputs & Sources'!$C$26/'2031 Projection'!C20/60 -> 1.3888889 | E6: few hours | F6: 500T / (6T/min) / 60.
A8: vs human cognition (doc basis: 1000 tok/min)
B9: Human token-equiv / min | C9: ='Inputs & Sources'!$C$27*'Inputs & Sources'!$C$28 -> 1500000000000 | E9: 1.5T | F9: 1.5B workers * 1000 tok/min.
B10: LLM : human token ratio | C10: ='2031 Projection'!C20/C9 -> 4 | E10: 4x | F10: LLM 6T/min vs human 1.5T/min.
A12: vs human cognition (Epoch basis: 240k tok/day)
B13: Human token-equiv / day | C13: ='Inputs & Sources'!$C$27*'Inputs & Sources'!$C$29 -> 360000000000000 | E13: - | F13: 1.5B * 240k.
B14: LLM tokens / day | C14: ='2031 Projection'!C20*1440 -> 8.64e+15 | E14: - | F14: 6T/min * 1440.
B15: LLM : human ratio (Epoch basis) | C15: =C14/C13 -> 24 | E15: - | F15: ~24x, not 4x: conclusion is sensitive to the human-cognition assumption.
A17: Revenue vs global wages
B18: Model-based revenue as % of wages | C18: ='2031 Projection'!C15/'Inputs & Sources'!$C$30 -> 0.04 | E18: >5% | F18: $2T / $50T wages = 4%. Doc says ">5% of wages".

Sheet Monte Carlo
A1: Monte Carlo - 2031 revenue & human parity
A2: LIVE 2,000-trial simulation (recalculates on open / F9). Authoritative 300k-trial run is in reproduce.py.
A5: Distribution parameters (blue = editable) | M5: SUMMARY (recalculates live)
B6: Parameter | C6: p1 | D6: p2 | E6: Distribution | F6: What this parameter is — and how to read p1 / p2 | J6: Implied median (real units) | M6: Estimate | N6: P5 | O6: P25 | P6: P50 | Q6: P75 | R6: P95 | S6: Mean
B7: growth mean / sd | C7: 3 | D7: 0.45 | E7: Normal, clipped [1.8,4.5] | F7: Annual growth of the global compute stock. p1 = mean (3x/yr), p2 = std dev (0.45). Drawn from a normal curve, then capped to the [1.8x, 4.5x] range so no absurd values appear. | J7: =C7 -> 3 | M7: M1 GPU | N7: =PERCENTILE(E22:E2021,0.05) -> 2.4725327e+12 | O7: =PERCENTILE(E22:E2021,0.25) -> 7.9377731e+12 | P7: =PERCENTILE(E22:E2021,0.5) -> 1.711876e+13 | Q7: =PERCENTILE(E22:E2021,0.75) -> 3.7491825e+13 | R7: =PERCENTILE(E22:E2021,0.95) -> 9.8085053e+13 | S7: =AVERAGE(E22:E2021) -> 3.0606657e+13
B8: h100_2026 lo / hi | C8: 16000000 | D8: 24000000 | E8: Uniform | F8: Starting global compute stock in 2026, in H100-equivalents. UNIFORM: every value between p1 (16M) and p2 (24M) is equally likely. Spans Epoch's ~16.5M up to the doc's 20M+. | J8: =(C8+D8)/2 -> 20000000 | M8: M2 model | N8: =PERCENTILE(F22:F2021,0.05) -> 5.4137614e+11 | O8: =PERCENTILE(F22:F2021,0.25) -> 1.4136337e+12 | P8: =PERCENTILE(F22:F2021,0.5) -> 2.8499707e+12 | Q8: =PERCENTILE(F22:F2021,0.75) -> 5.7552588e+12 | R8: =PERCENTILE(F22:F2021,0.95) -> 1.6359209e+13 | S8: =AVERAGE(F22:F2021) -> 4.9218084e+12
B9: M1 rev/chip mu / sigma | C9: 9.759647 | D9: 0.755291 | E9: Lognormal (90% CI $5k-$60k) | F9: METHOD 1 - 2026 revenue per inference chip (US$). LOGNORMAL: p1/p2 are the mean & std dev of the natural LOG, NOT dollars - this is why you see 9.76, not $9k. Median = e^9.76. 90% of draws fall in $5k-$60k (spans the $5k macro average and Anthropic's empirical ~$45k). | J9: =EXP(C9) -> 17320.516 | M9: M3 token | N9: =PERCENTILE(G22:G2021,0.05) -> 5.1526505e+11 | O9: =PERCENTILE(G22:G2021,0.25) -> 2.139515e+12 | P9: =PERCENTILE(G22:G2021,0.5) -> 6.5651869e+12 | Q9: =PERCENTILE(G22:G2021,0.75) -> 1.6665917e+13 | R9: =PERCENTILE(G22:G2021,0.95) -> 6.3498623e+13 | S9: =AVERAGE(G22:G2021) -> 1.7969941e+13
B10: M1 serving-share lo/hi | C10: 0.25 | D10: 0.55 | E10: Uniform | F10: METHOD 1 - share of the 2031 fleet actually serving frontier models. UNIFORM 25%-55% (the rest is training, experiments, smaller models, idle capacity). | J10: =(C10+D10)/2 -> 0.4 | M10: POOLED | N10: =PERCENTILE(H22:H2021,0.05) -> 6.4575554e+11 | O10: =PERCENTILE(H22:H2021,0.25) -> 2.3616937e+12 | P10: =PERCENTILE(H22:H2021,0.5) -> 6.481013e+12 | Q10: =PERCENTILE(H22:H2021,0.75) -> 1.8581822e+13 | R10: =PERCENTILE(H22:H2021,0.95) -> 6.8859761e+13 | S10: =AVERAGE(H22:H2021) -> 1.8274333e+13
B11: M1 price-decline lo/hi | C11: 0.25 | D11: 0.9 | E11: Uniform (rev/chip multiplier to 2031) | F11: METHOD 1 - how much of 2026 revenue-per-chip survives to 2031, as a multiplier. UNIFORM 0.25-0.9 = a 10%-75% fall, reflecting falling token prices over 5 years. | J11: =(C11+D11)/2 -> 0.575
B12: M2 copies mu / sigma | C12: 16.065415 | D12: 0.699874 | E12: Lognormal (90% CI 3M-30M) | F12: METHOD 2 - number of concurrent frontier model copies served in 2031. LOGNORMAL (log-space). Median = e^16.07 ~ 9.5M; 90% CI 3M-30M (brackets the doc's 10M). | J12: =EXP(C12) -> 9486829.3 | M12: Probabilities (pooled)
B13: M2 rev/copy mu / sigma | C13: 12.643807 | D13: 0.823116 | E13: Lognormal (90% CI $80k-$1.2M) | F13: METHOD 2 - annual revenue per model copy (US$). LOGNORMAL (log-space). Median = e^12.64 ~ $310k; 90% CI $80k-$1.2M (spans the doc's $200k and the 2026 case-study $1.07M). | J13: =EXP(C13) -> 309838.66 | M13: P(revenue > $2T) | N13: =COUNTIF(H22:H2021,">2000000000000")/2000 -> 0.7875
B14: M3 tok/s mu / sigma | C14: 27.631021 | D14: 1.255412 | E14: Lognormal (80% CI 0.2T-5T) | F14: METHOD 3 - total inference throughput in 2031 (tokens/second). LOGNORMAL (log-space). Median = e^27.63 ~ 1.0e12 (1 trillion tok/s); 80% CI 0.2T-5T (Epoch's late-2025 0.5-20B/s grown ~3x/yr). | J14: =EXP(C14) -> 9.9999988e+11 | M14: P(revenue > $1T) | N14: =COUNTIF(H22:H2021,">1000000000000")/2000 -> 0.9015
B15: M3 util lo / hi | C15: 0.05 | D15: 0.3 | E15: Uniform (Epoch range) | F15: METHOD 3 - average utilisation of that capacity. UNIFORM 5%-30% (Epoch's realistic inference-utilisation range). | J15: =(C15+D15)/2 -> 0.175 | M15: P(revenue > $10T) | N15: =COUNTIF(H22:H2021,">10000000000000")/2000 -> 0.3905
B16: M3 price mu / sigma | C16: 0.168236 | D16: 0.659287 | E16: Lognormal (90% CI $0.4-$3.5/Mtok) | F16: METHOD 3 - blended price per MILLION tokens (US$). LOGNORMAL (log-space). Median = e^0.168 ~ $1.18/Mtok; 90% CI $0.40-$3.50 (current DeepSeek output ~$0.87 up to the doc's $3.5). | J16: =EXP(C16) -> 1.1832158
B17: human workers lo/hi | C17: 1000000000 | D17: 1600000000 | E17: Uniform | F17: HUMAN-PARITY - number of white-collar workers in 2031. UNIFORM 1.0B-1.6B (current ~1.25B up to the doc's 1.5B). | J17: =(C17+D17)/2 -> 1300000000 | M17: Human-parity ratio
B18: human tok/min lo/hi | C18: 400 | D18: 1200 | E18: Uniform | F18: HUMAN-PARITY - tokens of cognition per worker per minute. UNIFORM 400-1200 (Epoch's ~500 from 380 wpm thinking, up to the doc's 1,000). | J18: =(C18+D18)/2 -> 800 | M18: P50 ratio | N18: =MEDIAN(K22:K2021) -> 8.9865766
M19: P(LLM > human-equiv) | N19: =COUNTIF(K22:K2021,">1")/2000 -> 0.9485
A20: Trials (2,000) - columns C..G are the three method revenues + pooled draw + human-parity ratio
B21: Trial | C21: growth | D21: H_2031 | E21: M1 GPU ($) | F21: M2 model ($) | G21: M3 token ($) | H21: Pooled ($) | I21: LLM tok/min | J21: Human/min | K21: Parity x | M21: Doc headline = $2T sits near the 25th percentile of the pooled distribution (i.e. conservative).
B22: 1 | C22: =MEDIAN(1.8,NORMINV(RAND(),$C$7,$D$7),4.5) -> 2.7540866 | D22: =($C$8+RAND()*($D$8-$C$8))*C22^5 -> 3.2111997e+09 | E22: =D22*($C$10+RAND()*($D$10-$C$10))*EXP(NORMINV(RAND(),$C$9,$D$9))*($C$11+RAND()*($D$11-$C$11)) -> 1.0033772e+13 | F22: =EXP(NORMINV(RAND(),$C$12,$D$12))*EXP(NORMINV(RAND(),$C$13,$D$13)) -> 9.5093211e+12 | G22: =EXP(NORMINV(RAND(),$C$14,$D$14))*($C$15+RAND()*($D$15-$C$15))*EXP(NORMINV(RAND(),$C$16,$D$16))/1000000*31536000 -> 5.9749632e+12 | H22: =CHOOSE(RANDBETWEEN(1,3),E22,F22,G22) -> 1.0033772e+13 | I22: =EXP(NORMINV(RAND(),$C$14,$D$14))*($C$15+RAND()*($D$15-$C$15))*60 -> 6.7911702e+12 | J22: =($C$17+RAND()*($D$17-$C$17))*($C$18+RAND()*($D$18-$C$18)) -> 1.1646808e+12 | K22: =I22/J22 -> 5.8309281
B23: 2 | C23: =MEDIAN(1.8,NORMINV(RAND(),$C$7,$D$7),4.5) -> 2.640126 | D23: =($C$8+RAND()*($D$8-$C$8))*C23^5 -> 2.8351962e+09 | E23: =D23*($C$10+RAND()*($D$10-$C$10))*EXP(NORMINV(RAND(),$C$9,$D$9))*($C$11+RAND()*($D$11-$C$11)) -> 2.7964397e+13 | F23: =EXP(NORMINV(RAND(),$C$12,$D$12))*EXP(NORMINV(RAND(),$C$13,$D$13)) -> 1.13548e+13 | G23: =EXP(NORMINV(RAND(),$C$14,$D$14))*($C$15+RAND()*($D$15-$C$15))*EXP(NORMINV(RAND(),$C$16,$D$16))/1000000*31536000 -> 3.0913541e+13 | H23: =CHOOSE(RANDBETWEEN(1,3),E23,F23,G23) -> 2.7964397e+13 | I23: =EXP(NORMINV(RAND(),$C$14,$D$14))*($C$15+RAND()*($D$15-$C$15))*60 -> 2.1760855e+12 | J23: =($C$17+RAND()*($D$17-$C$17))*($C$18+RAND()*($D$18-$C$18)) -> 8.3763673e+11 | K23: =I23/J23 -> 2.5978869
B24: 3 | C24: =MEDIAN(1.8,NORMINV(RAND(),$C$7,$D$7),4.5) -> 2.7061161 | D24: =($C$8+RAND()*($D$8-$C$8))*C24^5 -> 3.1878469e+09 | E24: =D24*($C$10+RAND()*($D$10-$C$10))*EXP(NORMINV(RAND(),$C$9,$D$9))*($C$11+RAND()*($D$11-$C$11)) -> 3.9436677e+13 | F24: =EXP(NORMINV(RAND(),$C$12,$D$12))*EXP(NORMINV(RAND(),$C$13,$D$13)) -> 9.4861207e+12 | G24: =EXP(NORMINV(RAND(),$C$14,$D$14))*($C$15+RAND()*($D$15-$C$15))*EXP(NORMINV(RAND(),$C$16,$D$16))/1000000*31536000 -> 5.7464545e+12 | H24: =CHOOSE(RANDBETWEEN(1,3),E24,F24,G24) -> 5.7464545e+12 | I24: =EXP(NORMINV(RAND(),$C$14,$D$14))*($C$15+RAND()*($D$15-$C$15))*60 -> 1.2742941e+12 | J24: =($C$17+RAND()*($D$17-$C$17))*($C$18+RAND()*($D$18-$C$18)) -> 7.2892716e+11 | K24: =I24/J24 -> 1.7481775
B25: 4 | C25: =MEDIAN(1.8,NORMINV(RAND(),$C$7,$D$7),4.5) -> 2.4414175 | D25: =($C$8+RAND()*($D$8-$C$8))*C25^5 -> 1.7210519e+09 | E25: =D25*($C$10+RAND()*($D$10-$C$10))*EXP(NORMINV(RAND(),$C$9,$D$9))*($C$11+RAND()*($D$11-$C$11)) -> 5.2071156e+12 | F25: =EXP(NORMINV(RAND(),$C$12,$D$12))*EXP(NORMINV(RAND(),$C$13,$D$13)) -> 4.0224597e+12 | G25: =EXP(NORMINV(RAND(),$C$14,$D$14))*($C$15+RAND()*($D$15-$C$15))*EXP(NORMINV(RAND(),$C$16,$D$16))/1000000*31536000 -> 5.5655012e+12 | H25: =CHOOSE(RANDBETWEEN(1,3),E25,F25,G25) -> 4.0224597e+12 | I25: =EXP(NORMINV(RAND(),$C$14,$D$14))*($C$15+RAND()*($D$15-$C$15))*60 -> 2.2741295e+13 | J25: =($C$17+RAND()*($D$17-$C$17))*($C$18+RAND()*($D$18-$C$18)) -> 1.0968304e+12 | K25: =I25/J25 -> 20.733648
B26: 5 | C26: =MEDIAN(1.8,NORMINV(RAND(),$C$7,$D$7),4.5) -> 2.8050484 | D26: =($C$8+RAND()*($D$8-$C$8))*C26^5 -> 3.0681997e+09 | E26: =D26*($C$10+RAND()*($D$10-$C$10))*EXP(NORMINV(RAND(),$C$9,$D$9))*($C$11+RAND()*($D$11-$C$11)) -> 1.3821359e+13 | F26: =EXP(NORMINV(RAND(),$C$12,$D$12))*EXP(NORMINV(RAND(),$C$13,$D$13)) -> 5.7646285e+12 | G26: =EXP(NORMINV(RAND(),$C$14,$D$14))*($C$15+RAND()*($D$15-$C$15))*EXP(NORMINV(RAND(),$C$16,$D$16))/1000000*31536000 -> 9.2170712e+12 | H26: =CHOOSE(RANDBETWEEN(1,3),E26,F26,G26) -> 9.2170712e+12 | I26: =EXP(NORMINV(RAND(),$C$14,$D$14))*($C$15+RAND()*($D$15-$C$15))*60 -> 8.0505786e+13 | J26: =($C$17+RAND()*($D$17-$C$17))*($C$18+RAND()*($D$18-$C$18)) -> 1.1052767e+12 | K26: =I26/J26 -> 72.837675
B27: 6 | C27: =MEDIAN(1.8,NORMINV(RAND(),$C$7,$D$7),4.5) -> 3.0395368 | D27: =($C$8+RAND()*($D$8-$C$8))*C27^5 -> 4.2647708e+09 | E27: =D27*($C$10+RAND()*($D$10-$C$10))*EXP(NORMINV(RAND(),$C$9,$D$9))*($C$11+RAND()*($D$11-$C$11)) -> 5.5454617e+13 | F27: =EXP(NORMINV(RAND(),$C$12,$D$12))*EXP(NORMINV(RAND(),$C$13,$D$13)) -> 1.0608679e+13 | G27: =EXP(NORMINV(RAND(),$C$14,$D$14))*($C$15+RAND()*($D$15-$C$15))*EXP(NORMINV(RAND(),$C$16,$D$16))/1000000*31536000 -> 5.9680634e+12 | H27: =CHOOSE(RANDBETWEEN(1,3),E27,F27,G27) -> 5.9680634e+12 | I27: =EXP(NORMINV(RAND(),$C$14,$D$14))*($C$15+RAND()*($D$15-$C$15))*60 -> 7.9374961e+13 | J27: =($C$17+RAND()*($D$17-$C$17))*($C$18+RAND()*($D$18-$C$18)) -> 8.9368667e+11 | K27: =I27/J27 -> 88.817439
B28: 7 | C28: =MEDIAN(1.8,NORMINV(RAND(),$C$7,$D$7),4.5) -> 2.6292849 | D28: =($C$8+RAND()*($D$8-$C$8))*C28^5 -> 2.0226574e+09 | E28: =D28*($C$10+RAND()*($D$10-$C$10))*EXP(NORMINV(RAND(),$C$9,$D$9))*($C$11+RAND()*($D$11-$C$11)) -> 4.5748296e+12 | F28: =EXP(NORMINV(RAND(),$C$12,$D$12))*EXP(NORMINV(RAND(),$C$13,$D$13)) -> 2.2020178e+12 | G28: =EXP(NORMINV(RAND(),$C$14,$D$14))*($C$15+RAND()*($D$15-$C$15))*EXP(NORMINV(RAND(),$C$16,$D$16))/1000000*31536000 -> 8.0330385e+12 | H28: =CHOOSE(RANDBETWEEN(1,3),E28,F28,G28) -> 4.5748296e+12 | I28: =EXP(NORMINV(RAND(),$C$14,$D$14))*($C$15+RAND()*($D$15-$C$15))*60 -> 1.1021194e+14 | J28: =($C$17+RAND()*($D$17-$C$17))*($C$18+RAND()*($D$18-$C$18)) -> 1.3372691e+12 | K28: =I28/J28 -> 82.415677
B29: 8 | C29: =MEDIAN(1.8,NORMINV(RAND(),$C$7,$D$7),4.5) -> 4.1098215 | D29: =($C$8+RAND()*($D$8-$C$8))*C29^5 -> 2.1876022e+10 | E29: =D29*($C$10+RAND()*($D$10-$C$10))*EXP(NORMINV(RAND(),$C$9,$D$9))*($C$11+RAND()*($D$11-$C$11)) -> 1.6766915e+14 | F29: =EXP(NORMINV(RAND(),$C$12,$D$12))*EXP(NORMINV(RAND(),$C$13,$D$13)) -> 9.4491139e+11 | G29: =EXP(NORMINV(RAND(),$C$14,$D$14))*($C$15+RAND()*($D$15-$C$15))*EXP(NORMINV(RAND(),$C$16,$D$16))/1000000*31536000 -> 3.5589679e+12 | H29: =CHOOSE(RANDBETWEEN(1,3),E29,F29,G29) -> 9.4491139e+11 | I29: =EXP(NORMINV(RAND(),$C$14,$D$14))*($C$15+RAND()*($D$15-$C$15))*60 -> 6.3652283e+12 | J29: =($C$17+RAND()*($D$17-$C$17))*($C$18+RAND()*($D$18-$C$18)) -> 1.0914125e+12 | K29: =I29/J29 -> 5.8321012
B30: 9 | C30: =MEDIAN(1.8,NORMINV(RAND(),$C$7,$D$7),4.5) -> 3.1595483 | D30: =($C$8+RAND()*($D$8-$C$8))*C30^5 -> 6.8945442e+09 | E30: =D30*($C$10+RAND()*($D$10-$C$10))*EXP(NORMINV(RAND(),$C$9,$D$9))*($C$11+RAND()*($D$11-$C$11)) -> 4.1089304e+13 | F30: =EXP(NORMINV(RAND(),$C$12,$D$12))*EXP(NORMINV(RAND(),$C$13,$D$13)) -> 4.048041e+12 | G30: =EXP(NORMINV(RAND(),$C$14,$D$14))*($C$15+RAND()*($D$15-$C$15))*EXP(NORMINV(RAND(),$C$16,$D$16))/1000000*31536000 -> 1.2455217e+12 | H30: =CHOOSE(RANDBETWEEN(1,3),E30,F30,G30) -> 4.048041e+12 | I30: =EXP(NORMINV(RAND(),$C$14,$D$14))*($C$15+RAND()*($D$15-$C$15))*60 -> 4.2381172e+12 | J30: =($C$17+RAND()*($D$17-$C$17))*($C$18+RAND()*($D$18-$C$18)) -> 1.5065787e+12 | K30: =I30/J30 -> 2.8130739
B31: 10 | C31: =MEDIAN(1.8,NORMINV(RAND(),$C$7,$D$7),4.5) -> 3.0712528 | D31: =($C$8+RAND()*($D$8-$C$8))*C31^5 -> 5.4373177e+09 | E31: =D31*($C$10+RAND()*($D$10-$C$10))*EXP(NORMINV(RAND(),$C$9,$D$9))*($C$11+RAND()*($D$11-$C$11)) -> 1.5500846e+13 | F31: =EXP(NORMINV(RAND(),$C$12,$D$12))*EXP(NORMINV(RAND(),$C$13,$D$13)) -> 4.7767636e+12 | G31: =EXP(NORMINV(RAND(),$C$14,$D$14))*($C$15+RAND()*($D$15-$C$15))*EXP(NORMINV(RAND(),$C$16,$D$16))/1000000*31536000 -> 3.1066887e+13 | H31: =CHOOSE(RANDBETWEEN(1,3),E31,F31,G31) -> 1.5500846e+13 | I31: =EXP(NORMINV(RAND(),$C$14,$D$14))*($C$15+RAND()*($D$15-$C$15))*60 -> 5.8447806e+12 | J31: =($C$17+RAND()*($D$17-$C$17))*($C$18+RAND()*($D$18-$C$18)) -> 1.6729634e+12 | K31: =I31/J31 -> 3.4936691
B32: 11 | C32: =MEDIAN(1.8,NORMINV(RAND(),$C$7,$D$7),4.5) -> 2.7547963 | D32: =($C$8+RAND()*($D$8-$C$8))*C32^5 -> 3.5775225e+09 | E32: =D32*($C$10+RAND()*($D$10-$C$10))*EXP(NORMINV(RAND(),$C$9,$D$9))*($C$11+RAND()*($D$11-$C$11)) -> 8.1185533e+12 | F32: =EXP(NORMINV(RAND(),$C$12,$D$12))*EXP(NORMINV(RAND(),$C$13,$D$13)) -> 6.5041493e+12 | G32: =EXP(NORMINV(RAND(),$C$14,$D$14))*($C$15+RAND()*($D$15-$C$15))*EXP(NORMINV(RAND(),$C$16,$D$16))/1000000*31536000 -> 7.0260871e+12 | H32: =CHOOSE(RANDBETWEEN(1,3),E32,F32,G32) -> 6.5041493e+12 | I32: =EXP(NORMINV(RAND(),$C$14,$D$14))*($C$15+RAND()*($D$15-$C$15))*60 -> 4.1622729e+13 | J32: =($C$17+RAND()*($D$17-$C$17))*($C$18+RAND()*($D$18-$C$18)) -> 9.0533517e+11 | K32: =I32/J32 -> 45.974939
B33: 12 | C33: =MEDIAN(1.8,NORMINV(RAND(),$C$7,$D$7),4.5) -> 2.4845042 | D33: =($C$8+RAND()*($D$8-$C$8))*C33^5 -> 2.0257821e+09 | E33: =D33*($C$10+RAND()*($D$10-$C$10))*EXP(NORMINV(RAND(),$C$9,$D$9))*($C$11+RAND()*($D$11-$C$11)) -> 6.4414961e+12 | F33: =EXP(NORMINV(RAND(),$C$12,$D$12))*EXP(NORMINV(RAND(),$C$13,$D$13)) -> 9.0629829e+11 | G33: =EXP(NORMINV(RAND(),$C$14,$D$14))*($C$15+RAND()*($D$15-$C$15))*EXP(NORMINV(RAND(),$C$16,$D$16))/1000000*31536000 -> 4.7863377e+12 | H33: =CHOOSE(RANDBETWEEN(1,3),E33,F33,G33) -> 4.7863377e+12 | I33: =EXP(NORMINV(RAND(),$C$14,$D$14))*($C$15+RAND()*($D$15-$C$15))*60 -> 3.5744673e+12 | J33: =($C$17+RAND()*($D$17-$C$17))*($C$18+RAND()*($D$18-$C$18)) -> 1.0606494e+12 | K33: =I33/J33 -> 3.3700745
... B2021: 2000 | C2021: =MEDIAN(1.8,NORMINV(RAND(),$C$7,$D$7),4.5) -> 2.1272511 | D2021: =($C$8+RAND()*($D$8-$C$8))*C2021^5 -> 7.7850457e+08 | E2021: =D2021*($C$10+RAND()*($D$10-$C$10))*EXP(NORMINV(RAND(),$C$9,$D$9))*($C$11+RAND()*($D$11-$C$11)) -> 3.8258499e+12 | F2021: =EXP(NORMINV(RAND(),$C$12,$D$12))*EXP(NORMINV(RAND(),$C$13,$D$13)) -> 2.5770839e+12 | G2021: =EXP(NORMINV(RAND(),$C$14,$D$14))*($C$15+RAND()*($D$15-$C$15))*EXP(NORMINV(RAND(),$C$16,$D$16))/1000000*31536000 -> 3.2068846e+13 | H2021: =CHOOSE(RANDBETWEEN(1,3),E2021,F2021,G2021) -> 2.5770839e+12 | I2021: =EXP(NORMINV(RAND(),$C$14,$D$14))*($C$15+RAND()*($D$15-$C$15))*60 -> 1.1802675e+13 | J2021: =($C$17+RAND()*($D$17-$C$17))*($C$18+RAND()*($D$18-$C$18)) -> 4.2018845e+11 | K2021: =I2021/J2021 -> 28.089003

Sheet Scenario L-B-H
A1: Deterministic scenario / tornado
A2: Token-method revenue ($/yr), one driver at a time low/high, others at base. Shows what moves the answer.
A5: Base case (token method)
B6: tok/s capacity | C6: 1000000000000
B7: utilisation | C7: 0.1
B8: price $/Mtok | C8: 0.83
B9: Base revenue/yr | C9: =C6*C7*C8/1000000*31536000 -> 2617488000000
A11: Tornado (hold others at base)
B12: Driver | C12: Low | D12: High | E12: Rev @ Low | F12: Rev @ High | G12: Swing
B13: tok/s capacity | C13: 300000000000 | D13: 2000000000000 | E13: =C13*$C$7*$C$8/1000000*31536000 -> 785246400000 | F13: =D13*$C$7*$C$8/1000000*31536000 -> 5234976000000 | G13: =ABS(F13-E13) -> 4449729600000
B14: utilisation | C14: 0.05 | D14: 0.3 | E14: =$C$6*C14*$C$8/1000000*31536000 -> 1308744000000 | F14: =$C$6*D14*$C$8/1000000*31536000 -> 7852464000000 | G14: =ABS(F14-E14) -> 6543720000000
B15: price $/Mtok | C15: 0.4 | D15: 3.5 | E15: =$C$6*$C$7*C15/1000000*31536000 -> 1261440000000 | F15: =$C$6*$C$7*D15/1000000*31536000 -> 11037600000000 | G15: =ABS(F15-E15) -> 9776160000000
B17: Capacity and price dominate the spread; utilisation matters least. Mirrors the Spearman ranks in reproduce.py.
